{"liveRoom1": {"liveStatus": "reser", "nickname": "\u5b89\u5fbd\u7535\u4fe1", "anchorId": "39", "liveId": 48, "start_time": "2022-11-30 20:00:00", "period": 108, "avator": "https://privilege.e.189.cn/source/img/1594781957216.png"}, "liveRoom2": {"liveStatus": "reser", "nickname": "\u91cd\u5e86\u7535\u4fe1", "anchorId": "1313", "liveId": 110, "start_time": "2022-11-30 15:31:00", "period": 62, "avator": "https://xbk.189.cn/dximg/htimg/GjMLJcI0eY20a8pMR5D7OqA66mzsRsUHE6nvqfbK.jpeg"}, "liveRoom3": {"liveStatus": "reser", "nickname": "\u9102\u5c14\u591a\u65af\u7535\u4fe1", "anchorId": "3478", "liveId": 3221, "start_time": "2022-11-30 16:30:00", "period": 4, "avator": "https://xbk.189.cn/dximg/htimg/Gl6vdEkEI2cY9ZywGWxI6vLxcqW4K3M32PDjuDRD.jpeg"}, "liveRoom4": {"liveStatus": "reser", "nickname": "\u5c71\u4e1c\u7535\u4fe1", "anchorId": "44", "liveId": 71, "start_time": "2022-11-30 17:30:00", "period": 50, "avator": "https://privilege.e.189.cn/source/img/1594781957216.png"}, "liveRoom5": {"liveStatus": "reser", "nickname": "\u5858\u82f1\u8425\u4e1a\u5385", "anchorId": "2461", "liveId": 3505, "start_time": "2022-11-30 15:00:00", "period": 7, "avator": "https://xbk.189.cn/dximg/htimg/QcOM0n7jEFJUphoGuxKBJKYKiBEKu00G6vMF3v1D.jpeg"}, "liveRoom6": {"liveStatus": "reser", "nickname": "\u90fd\u5b89\u5c4f\u5357\u8857\u8425\u4e1a\u5385", "anchorId": "2453", "liveId": 3494, "start_time": "2022-11-30 16:30:00", "period": 7, "avator": "https://xbk.189.cn/dximg/htimg/Ryv2XjsPsdgmB3XKSMohSGvpWovayxMmkUvdzdNe.jpeg"}, "liveRoom7": {"liveStatus": "reser", "nickname": "\u56db\u5ddd\u7535\u4fe1", "anchorId": "34", "liveId": 1988, "start_time": "2022-11-30 15:00:00", "period": 15, "avator": "https://wapmkt.189.cn:7443/download/userfiles/fileupload/202208/1557671345255387138.jpg"}, "liveRoom8": {"liveStatus": "reser", "nickname": "\u9ed4\u4e1c\u5357\u7535\u4fe1", "anchorId": "4036", "liveId": 2207, "start_time": "2022-11-30 15:59:00", "period": 15, "avator": "https://xbk.189.cn/dximg/htimg/CnH9arLi0ybF001lWb0cplQONZJKuuH9tGTkLUcV.jpeg"}, "liveRoom9": {"liveStatus": "reser", "nickname": "\u9ed4\u5357\u5206\u516c\u53f8", "anchorId": "2429", "liveId": 2208, "start_time": "2022-11-30 18:29:00", "period": 19, "avator": "https://xbk.189.cn/dximg/htimg/d8EmiXfvHKvPUryrhHGRO4eWNPu8bikUEwFXdGY7.jpeg"}, "liveRoom10": {"liveStatus": "reser", "nickname": "\u7984\u529d\u76f4\u8425\u4e2d\u5fc3\u8425\u4e1a\u5385", "anchorId": "4225", "liveId": 4605, "start_time": "2022-11-30 19:00:00", "period": 1, "avator": "https://xbk.189.cn/dximg/htimg/Uzx3DSVhucQ2WqtfvrVfmGuTenVk0ljxWstRxUIW.jpeg"}, "liveRoom11": {"liveStatus": "reser", "nickname": "\u5357\u6da7\u53bf\u5bcc\u6c11\u8def\u8425\u4e1a\u5385", "anchorId": "3729", "liveId": 4479, "start_time": "2022-11-30 19:30:00", "period": 11, "avator": "https://xbk.189.cn/dximg/htimg/AzwAMCXzSduBBiKbDMC4GGfdgRgYSy1TtOLHBLDr.jpeg"}, "liveRoom12": {"liveStatus": "reser", "nickname": "\u5170\u5dde\u5e7f\u573a\u897f\u53e3\u8425\u4e1a\u5385", "anchorId": "4257", "liveId": 4664, "start_time": "2022-11-30 16:00:00", "period": 1, "avator": "https://xbk.189.cn/dximg/htimg/AzwAMCXzSduBBiKbDMC4GGfdgRgYSy1TtOLHBLDr.jpeg"}}
